simpsons_rdf/__init__.py
simpsons_rdf/simpsons.ttl
simpsons_rdf-0.3.0.dist-info/METADATA
simpsons_rdf-0.3.0.dist-info/WHEEL
simpsons_rdf-0.3.0.dist-info/RECORD
