Metadata-Version: 2.3
Name: simpsons-rdf
Version: 0.3.0
Summary: An example rdflib graph with some simpsons.
Author: Natanael Arndt
Author-email: arndtn@gmail.com
Requires-Python: >=3.9,<4.0
Classifier: Programming Language :: Python :: 3
Classifier: Programming Language :: Python :: 3.9
Classifier: Programming Language :: Python :: 3.10
Classifier: Programming Language :: Python :: 3.11
Classifier: Programming Language :: Python :: 3.12
Classifier: Programming Language :: Python :: 3.13
Requires-Dist: rdflib (>=7.1.4,<8.0.0)
Project-URL: Repository, https://github.com/white-gecko/simpsons
